{"status":"success","keywords":"","total":12153,"pages":"<em onclick=\"pageClick(1)\" style=\"cursor: default;\">\u9996\u9875<\/em><span onclick=\"pageClick(431)\" style=\"cursor:default;\">431<\/span><span onclick=\"pageClick(432)\" style=\"cursor:default;\">432<\/span><span class=\"active\" style=\"cursor:default;\">433<\/span><span onclick=\"pageClick(434)\" style=\"cursor:default;\">434<\/span><span onclick=\"pageClick(435)\" style=\"cursor:default;\">435<\/span><em onclick=\"pageClick(1216)\" style=\"cursor: default;\">\u672b\u9875<\/em>","curPage":433,"origin":"","list":[{"title":"\u5c31\u53e4\u5df4\u9769\u547d\u80dc\u522960\u5468\u5e74 \u4e60\u8fd1\u5e73\u5411\u53e4\u5df4\u9886\u5bfc\u4eba\u81f4\u8d3a\u7535","input_date":"2019-01-02 07:26:30","article_id":"30498243","publishdate":"0","publishdep":"","origin_name":"\u4eba\u6c11\u7f51\uff0d\u4eba\u6c11\u65e5\u62a5"},{"title":"\u4e60\u8fd1\u5e73\uff1a\u8fa9\u8bc1\u552f\u7269\u4e3b\u4e49\u662f\u4e2d\u56fd\u5171\u4ea7\u515a\u4eba\u7684\u4e16\u754c\u89c2\u548c\u65b9\u6cd5\u8bba","input_date":"2019-01-01 11:26:47","article_id":"30497908","publishdate":"0","publishdep":"","origin_name":"\u6c42\u662f"},{"title":"\u4e60\u8fd1\u5e73\u5c31\u53e4\u5df4\u9769\u547d\u80dc\u522960\u5468\u5e74\u5411\u53e4\u5df4\u9886\u5bfc\u4eba\u81f4\u8d3a\u7535","input_date":"2019-01-01 10:17:42","article_id":"30497873","publishdate":"0","publishdep":"","origin_name":"\u65b0\u534e\u793e"},{"title":"\u4e2d\u4fc4\u4e24\u56fd\u5143\u9996\u4e92\u81f4\u65b0\u5e74\u8d3a\u7535","input_date":"2019-01-01 07:53:13","article_id":"30497655","publishdate":"0","publishdep":"","origin_name":"\u4eba\u6c11\u7f51\uff0d\u4eba\u6c11\u65e5\u62a5"},{"title":"\u4e2d\u7f8e\u4e24\u56fd\u9886\u5bfc\u4eba\u4e92\u81f4\u8d3a\u4fe1\u5e86\u795d\u4e24\u56fd\u5efa\u4ea440\u5468\u5e74","input_date":"2019-01-01 07:53:13","article_id":"30497656","publishdate":"0","publishdep":"","origin_name":"\u4eba\u6c11\u7f51\uff0d\u4eba\u6c11\u65e5\u62a5"},{"title":"\u56fd\u5bb6\u4e3b\u5e2d\u4e60\u8fd1\u5e73\u53d1\u8868\u4e8c\u3007\u4e00\u4e5d\u5e74\u65b0\u5e74\u8d3a\u8bcd","input_date":"2019-01-01 07:53:13","article_id":"30497657","publishdate":"0","publishdep":"","origin_name":"\u4eba\u6c11\u7f51\uff0d\u4eba\u6c11\u65e5\u62a5"},{"title":"\u300a\u544a\u53f0\u6e7e\u540c\u80de\u4e66\u300b\u53d1\u886840\u5468\u5e74\u7eaa\u5ff5\u4f1a1\u67082\u65e5\u4e0a\u5348\u5728\u4eac\u4e3e\u884c","input_date":"2019-01-01 07:53:13","article_id":"30497659","publishdate":"0","publishdep":"","origin_name":"\u4eba\u6c11\u7f51\uff0d\u4eba\u6c11\u65e5\u62a5"},{"title":"\u56fd\u5bb6\u4e3b\u5e2d\u4e60\u8fd1\u5e73\u53d1\u8868\u4e8c\u3007\u4e00\u4e5d\u5e74\u65b0\u5e74\u8d3a\u8bcd","input_date":"2018-12-31 23:12:45","article_id":"30497577","publishdate":"0","publishdep":"","origin_name":"\u65b0\u534e\u793e"},{"title":"\u4e2d\u4fc4\u4e24\u56fd\u5143\u9996\u4e92\u81f4\u65b0\u5e74\u8d3a\u7535 \u4e2d\u4fc4\u4e24\u56fd\u603b\u7406\u4e92\u81f4\u65b0\u5e74\u8d3a\u7535","input_date":"2018-12-31 12:19:44","article_id":"30497433","publishdate":"0","publishdep":"","origin_name":"\u65b0\u534e\u793e"},{"title":"\u300a\u544a\u53f0\u6e7e\u540c\u80de\u4e66\u300b\u53d1\u886840\u5468\u5e74\u7eaa\u5ff5\u4f1a1\u67082\u65e5\u4e0a\u5348\u5728\u4eac\u4e3e\u884c \u4e60\u8fd1\u5e73\u5c06\u51fa\u5e2d\u7eaa\u5ff5\u4f1a\u5e76\u53d1\u8868\u91cd\u8981\u8bb2\u8bdd","input_date":"2018-12-31 12:17:57","article_id":"30497432","publishdate":"0","publishdep":"","origin_name":"\u65b0\u534e\u793e"}]}