{"status":"success","keywords":"","total":12153,"pages":"<em onclick=\"pageClick(1)\" style=\"cursor: default;\">\u9996\u9875<\/em><span onclick=\"pageClick(450)\" style=\"cursor:default;\">450<\/span><span onclick=\"pageClick(451)\" style=\"cursor:default;\">451<\/span><span class=\"active\" style=\"cursor:default;\">452<\/span><span onclick=\"pageClick(453)\" style=\"cursor:default;\">453<\/span><span onclick=\"pageClick(454)\" style=\"cursor:default;\">454<\/span><em onclick=\"pageClick(1216)\" style=\"cursor: default;\">\u672b\u9875<\/em>","curPage":452,"origin":"","list":[{"title":"\u4e60\u8fd1\u5e73\u7ed3\u675f\u5bf9\u5df4\u5e03\u4e9a\u65b0\u51e0\u5185\u4e9a\u72ec\u7acb\u56fd\u3001\u6587\u83b1\u8fbe\u9c81\u8428\u5170\u56fd\u3001\u83f2\u5f8b\u5bbe\u5171\u548c\u56fd\u56fd\u4e8b\u8bbf\u95ee\u5e76\u5728\u5df4\u65b0\u540c\u5efa\u4ea4\u592a\u5e73\u6d0b\u5c9b\u56fd\u9886\u5bfc\u4eba\u4f1a\u6664\uff0c\u51fa\u5e2d\u4e9a\u592a\u7ecf\u5408\u7ec4\u7ec7\u7b2c\u4e8c\u5341\u516d\u6b21\u9886\u5bfc\u4eba\u975e\u6b63\u5f0f\u4f1a\u8bae\u56de\u5230\u5317\u4eac","input_date":"2018-11-21 19:03:04","article_id":"30414313","publishdate":"0","publishdep":"","origin_name":"\u65b0\u534e\u7f51"},{"title":"\u4e60\u8fd1\u5e73\u4f1a\u89c1\u83f2\u5f8b\u5bbe\u4f17\u8bae\u957f\u963f\u7f57\u7ea6\u548c\u53c2\u8bae\u957f\u7d22\u6258","input_date":"2018-11-21 13:41:19","article_id":"30413868","publishdate":"0","publishdep":"","origin_name":"\u65b0\u534e\u793e"},{"title":"\u4e60\u8fd1\u5e73\u8bb2\u6545\u4e8b\uff1a\u6cbb\u56fd\u6709\u5e38\uff0c\u800c\u5229\u6c11\u4e3a\u672c","input_date":"2018-11-21 06:58:53","article_id":"30412325","publishdate":"0","publishdep":"","origin_name":"\u4eba\u6c11\u7f51\uff0d\u4eba\u6c11\u65e5\u62a5\u6d77\u5916\u7248"},{"title":"\u4e60\u8fd1\u5e73\u62b5\u8fbe\u9a6c\u5c3c\u62c9","input_date":"2018-11-21 06:52:38","article_id":"30412303","publishdate":"0","publishdep":"","origin_name":"\u4eba\u6c11\u7f51\uff0d\u4eba\u6c11\u65e5\u62a5"},{"title":"\u4e60\u8fd1\u5e73\u540c\u83f2\u5f8b\u5bbe\u603b\u7edf\u675c\u7279\u5c14\u7279\u4e3e\u884c\u4f1a\u8c08","input_date":"2018-11-21 06:52:38","article_id":"30412304","publishdate":"0","publishdep":"","origin_name":"\u4eba\u6c11\u7f51\uff0d\u4eba\u6c11\u65e5\u62a5"},{"title":"\u4e60\u8fd1\u5e73\u540c\u5df4\u52d2\u65af\u5766\u603b\u7edf\u963f\u5df4\u65af\u5c31\u4e2d\u5df4\u5efa\u4ea430\u5468\u5e74\u4e92\u81f4\u8d3a\u7535","input_date":"2018-11-21 06:52:38","article_id":"30412305","publishdate":"0","publishdep":"","origin_name":"\u4eba\u6c11\u7f51\uff0d\u4eba\u6c11\u65e5\u62a5"},{"title":"\u4e60\u8fd1\u5e73\u540c\u83f2\u5f8b\u5bbe\u603b\u7edf\u675c\u7279\u5c14\u7279\u4e3e\u884c\u4f1a\u8c08","input_date":"2018-11-20 21:17:21","article_id":"30412128","publishdate":"0","publishdep":"","origin_name":"\u65b0\u534e\u793e"},{"title":"\u4e60\u8fd1\u5e73\u540c\u5df4\u52d2\u65af\u5766\u603b\u7edf\u963f\u5df4\u65af\u5c31\u4e2d\u5df4\u5efa\u4ea430\u5468\u5e74\u4e92\u81f4\u8d3a\u7535","input_date":"2018-11-20 18:08:06","article_id":"30412032","publishdate":"0","publishdep":"","origin_name":"\u65b0\u534e\u793e"},{"title":"\u4e60\u8fd1\u5e73\u62b5\u8fbe\u9a6c\u5c3c\u62c9 \u5f00\u59cb\u5bf9\u83f2\u5f8b\u5bbe\u5171\u548c\u56fd\u8fdb\u884c\u56fd\u4e8b\u8bbf\u95ee","input_date":"2018-11-20 14:11:53","article_id":"30411510","publishdate":"0","publishdep":"","origin_name":"\u65b0\u534e\u793e"},{"title":"\u4e60\u8fd1\u5e73\u62b5\u8fbe\u9a6c\u5c3c\u62c9 \u5f00\u59cb\u5bf9\u83f2\u5f8b\u5bbe\u8fdb\u884c\u56fd\u4e8b\u8bbf\u95ee","input_date":"2018-11-20 12:06:17","article_id":"30411357","publishdate":"0","publishdep":"","origin_name":"\u65b0\u534e\u793e"}]}