{"status":"success","keywords":"","total":12153,"pages":"<em onclick=\"pageClick(1)\" style=\"cursor: default;\">\u9996\u9875<\/em><span onclick=\"pageClick(558)\" style=\"cursor:default;\">558<\/span><span onclick=\"pageClick(559)\" style=\"cursor:default;\">559<\/span><span class=\"active\" style=\"cursor:default;\">560<\/span><span onclick=\"pageClick(561)\" style=\"cursor:default;\">561<\/span><span onclick=\"pageClick(562)\" style=\"cursor:default;\">562<\/span><em onclick=\"pageClick(1216)\" style=\"cursor: default;\">\u672b\u9875<\/em>","curPage":560,"origin":"","list":[{"title":"\u5341\u4e5d\u5c4a\u4e2d\u592e\u7eaa\u59d4\u4e8c\u6b21\u5168\u4f1a\u95ed\u5e55","input_date":"2018-01-13 11:59:18","article_id":"29762855","publishdate":"0","publishdep":"","origin_name":"\u4e2d\u592e\u7eaa\u59d4\u76d1\u5bdf\u90e8\u7f51\u7ad9"},{"title":"\u4e2d\u5171\u4e2d\u592e\u653f\u6cbb\u5c40\u53ec\u5f00\u4f1a\u8bae \u8ba8\u8bba\u62df\u63d0\u8bf7\u5341\u4e5d\u5c4a\u4e8c\u4e2d\u5168\u4f1a\u5ba1\u8bae\u7684\u6587\u4ef6 \u4e2d\u5171\u4e2d\u592e\u603b\u4e66\u8bb0\u4e60\u8fd1\u5e73\u4e3b\u6301\u4f1a\u8bae","input_date":"2018-01-13 08:20:58","article_id":"29762523","publishdate":"0","publishdep":"","origin_name":"\u4eba\u6c11\u7f51\uff0d\u4eba\u6c11\u65e5\u62a5"},{"title":"\u4e60\u8fd1\u5e73\u65b0\u5e74\u8d3a\u8bcd\u7684\u98ce\u683c\u53ca\u7279\u70b9","input_date":"2018-01-12 14:53:49","article_id":"29761987","publishdate":"0","publishdep":"","origin_name":"\u65b0\u534e\u7f51"},{"title":"\u4e2d\u5171\u4e2d\u592e\u653f\u6cbb\u5c40\u53ec\u5f00\u4f1a\u8bae \u4e60\u8fd1\u5e73\u4e3b\u6301","input_date":"2018-01-12 14:01:50","article_id":"29761859","publishdate":"0","publishdep":"","origin_name":"\u65b0\u534e\u793e"},{"title":"\u5168\u9762\u8d2f\u5f7b\u843d\u5b9e\u515a\u7684\u5341\u4e5d\u5927\u7cbe\u795e \n\u4ee5\u6c38\u8fdc\u5728\u8def\u4e0a\u7684\u6267\u7740\u628a\u4ece\u4e25\u6cbb\u515a\u5f15\u5411\u6df1\u5165","input_date":"2018-01-12 08:13:48","article_id":"29760596","publishdate":"0","publishdep":"","origin_name":"\u4eba\u6c11\u7f51\uff0d\u4eba\u6c11\u65e5\u62a5"},{"title":"\u4e60\u8fd1\u5e73\u5e94\u7ea6\u540c\u97e9\u56fd\u603b\u7edf\u6587\u5728\u5bc5\u901a\u7535\u8bdd","input_date":"2018-01-12 07:21:01","article_id":"29760189","publishdate":"0","publishdep":"","origin_name":"\u4eba\u6c11\u7f51\uff0d\u4eba\u6c11\u65e5\u62a5"},{"title":"\u4e60\u8fd1\u5e73\uff1a\u5168\u9762\u8d2f\u5f7b\u843d\u5b9e\u515a\u7684\u5341\u4e5d\u5927\u7cbe\u795e \u4ee5\u6c38\u8fdc\u5728\u8def\u4e0a\u7684\u6267\u7740\u628a\u4ece\u4e25\u6cbb\u515a\u5f15\u5411\u6df1\u5165","input_date":"2018-01-12 07:21:01","article_id":"29760190","publishdate":"0","publishdep":"","origin_name":"\u4eba\u6c11\u7f51\uff0d\u4eba\u6c11\u65e5\u62a5"},{"title":"\u4e60\u8fd1\u5e73\u4f1a\u89c1\u82f1\u56fd\u524d\u9996\u76f8\u5361\u6885\u4f26","input_date":"2018-01-12 07:21:01","article_id":"29760191","publishdate":"0","publishdep":"","origin_name":"\u4eba\u6c11\u7f51\uff0d\u4eba\u6c11\u65e5\u62a5"},{"title":"\u4e60\u8fd1\u5e73\u4f1a\u89c1\u82f1\u56fd\u524d\u9996\u76f8\u5361\u6885\u4f26","input_date":"2018-01-11 20:51:58","article_id":"29759977","publishdate":"0","publishdep":"","origin_name":"\u65b0\u534e\u793e"},{"title":"\u4e60\u8fd1\u5e73\u5e94\u7ea6\u540c\u97e9\u56fd\u603b\u7edf\u6587\u5728\u5bc5\u901a\u7535\u8bdd","input_date":"2018-01-11 20:16:06","article_id":"29759956","publishdate":"0","publishdep":"","origin_name":"\u65b0\u534e\u793e"}]}