{"status":"success","keywords":"","total":12153,"pages":"<em onclick=\"pageClick(1)\" style=\"cursor: default;\">\u9996\u9875<\/em><span onclick=\"pageClick(630)\" style=\"cursor:default;\">630<\/span><span onclick=\"pageClick(631)\" style=\"cursor:default;\">631<\/span><span class=\"active\" style=\"cursor:default;\">632<\/span><span onclick=\"pageClick(633)\" style=\"cursor:default;\">633<\/span><span onclick=\"pageClick(634)\" style=\"cursor:default;\">634<\/span><em onclick=\"pageClick(1216)\" style=\"cursor: default;\">\u672b\u9875<\/em>","curPage":632,"origin":"","list":[{"title":"\u4e60\u8fd1\u5e73\u81f4\u7b2c\u516b\u5c4a\u6e05\u6d01\u80fd\u6e90\u90e8\u957f\u7ea7\u4f1a\u8bae\u548c\u7b2c\u4e8c\u5c4a\u521b\u65b0\u4f7f\u547d\u90e8\u957f\u7ea7\u4f1a\u8bae\u7684\u8d3a\u4fe1","input_date":"2017-06-08 07:27:31","article_id":"29325188","publishdate":"0","publishdep":"","origin_name":"\u4eba\u6c11\u7f51\uff0d\u4eba\u6c11\u65e5\u62a5"},{"title":"\u4e60\u8fd1\u5e73\u81f4\u7b2c\u516b\u5c4a\u6e05\u6d01\u80fd\u6e90\u90e8\u957f\u7ea7\u4f1a\u8bae\u548c\u7b2c\u4e8c\u5c4a\u521b\u65b0\u4f7f\u547d\u90e8\u957f\u7ea7\u4f1a\u8bae\u7684\u8d3a\u4fe1","input_date":"2017-06-07 19:19:16","article_id":"29324766","publishdate":"0","publishdep":"","origin_name":"\u65b0\u534e\u793e"},{"title":"\u4e60\u8fd1\u5e73\u5411\u7b2c\u516b\u5c4a\u6e05\u6d01\u80fd\u6e90\u90e8\u957f\u7ea7\u4f1a\u8bae\u548c\u7b2c\u4e8c\u5c4a\u521b\u65b0\u4f7f\u547d\u90e8\u957f\u7ea7\u4f1a\u8bae\u81f4\u8d3a\u4fe1","input_date":"2017-06-07 17:51:10","article_id":"29324732","publishdate":"0","publishdep":"","origin_name":"\u65b0\u534e\u793e"},{"title":"\u4e60\u8fd1\u5e73\u79bb\u4eac\u5bf9\u54c8\u8428\u514b\u65af\u5766\u5171\u548c\u56fd\u8fdb\u884c\u56fd\u4e8b\u8bbf\u95ee\u5e76\u51fa\u5e2d\u4e0a\u6d77\u5408\u4f5c\u7ec4\u7ec7\u6210\u5458\u56fd\u5143\u9996\u7406\u4e8b\u4f1a\u7b2c\u5341\u4e03\u6b21\u4f1a\u8bae\u548c\u963f\u65af\u5854\u7eb3\u4e13\u9879\u4e16\u535a\u4f1a\u5f00\u5e55\u5f0f","input_date":"2017-06-07 15:52:22","article_id":"29324545","publishdate":"0","publishdep":"","origin_name":"\u65b0\u534e\u793e"},{"title":"\u4e60\u8fd1\u5e73\u5728\u54c8\u8428\u514b\u65af\u5766\u5a92\u4f53\u53d1\u8868\u7f72\u540d\u6587\u7ae0","input_date":"2017-06-07 15:45:30","article_id":"29324528","publishdate":"0","publishdep":"","origin_name":"\u65b0\u534e\u793e"},{"title":"\u4e60\u8fd1\u5e73\u8c08\u4fe1\u4ef0\u4fe1\u5ff5","input_date":"2017-06-07 07:38:25","article_id":"29322419","publishdate":"0","publishdep":"","origin_name":"\u4eba\u6c11\u7f51\uff0d\u4eba\u6c11\u65e5\u62a5\u6d77\u5916\u7248"},{"title":"\u4e60\u8fd1\u5e73\u4f1a\u89c1\u7f8e\u56fd\u52a0\u5229\u798f\u5c3c\u4e9a\u5dde\u5dde\u957f","input_date":"2017-06-07 07:30:40","article_id":"29322378","publishdate":"0","publishdep":"","origin_name":"\u4eba\u6c11\u7f51\uff0d\u4eba\u6c11\u65e5\u62a5"},{"title":"\u4e60\u8fd1\u5e73\u54112017\u5e74\u201c\u5168\u7403\u822a\u5929\u63a2\u7d22\u5927\u4f1a\u201d\u81f4\u8d3a\u4fe1","input_date":"2017-06-07 07:30:40","article_id":"29322379","publishdate":"0","publishdep":"","origin_name":"\u4eba\u6c11\u7f51\uff0d\u4eba\u6c11\u65e5\u62a5"},{"title":"\u4e60\u8fd1\u5e73\u548c\u7eb3\u624e\u5c14\u5df4\u8036\u592b\u4e3a\u753b\u518c\u81f4\u8f9e","input_date":"2017-06-07 07:30:40","article_id":"29322380","publishdate":"0","publishdep":"","origin_name":"\u4eba\u6c11\u7f51\uff0d\u4eba\u6c11\u65e5\u62a5"},{"title":"\u4e60\u8fd1\u5e73\u4f1a\u89c1\u7f8e\u56fd\u52a0\u5229\u798f\u5c3c\u4e9a\u5dde\u5dde\u957f\u5e03\u6717","input_date":"2017-06-06 18:57:01","article_id":"29321982","publishdate":"0","publishdep":"","origin_name":"\u65b0\u534e\u793e"}]}