{"status":"success","keywords":"","total":12153,"pages":"<em onclick=\"pageClick(1)\" style=\"cursor: default;\">\u9996\u9875<\/em><span onclick=\"pageClick(1095)\" style=\"cursor:default;\">1095<\/span><span onclick=\"pageClick(1096)\" style=\"cursor:default;\">1096<\/span><span class=\"active\" style=\"cursor:default;\">1097<\/span><span onclick=\"pageClick(1098)\" style=\"cursor:default;\">1098<\/span><span onclick=\"pageClick(1099)\" style=\"cursor:default;\">1099<\/span><em onclick=\"pageClick(1216)\" style=\"cursor: default;\">\u672b\u9875<\/em>","curPage":1097,"origin":"","list":[{"title":"\u4e60\u8fd1\u5e73\u5728\u7eaa\u5ff5\u6bdb\u6cfd\u4e1c\u540c\u5fd7\u8bde\u8fb0120\u5468\u5e74\u5ea7\u8c08\u4f1a\u4e0a\u7684\u8bb2\u8bdd","input_date":"2013-12-27 07:07:21","article_id":"23954163","publishdate":"0","publishdep":"","origin_name":"\u4eba\u6c11\u7f51\uff0d\u4eba\u6c11\u65e5\u62a5"},{"title":"\u7eaa\u5ff5\u6bdb\u6cfd\u4e1c\u8bde\u8fb0120\u5468\u5e74\u5ea7\u8c08\u4f1a\u4e3e\u884c \u4e60\u8fd1\u5e73\u53d1\u8868\u91cd\u8981\u8bb2\u8bdd","input_date":"2013-12-27 07:07:10","article_id":"23954162","publishdate":"0","publishdep":"","origin_name":"\u4eba\u6c11\u7f51\uff0d\u4eba\u6c11\u65e5\u62a5"},{"title":"\u4e60\u8fd1\u5e73\u5728\u7eaa\u5ff5\u6bdb\u6cfd\u4e1c\u540c\u5fd7\u8bde\u8fb0120\u5468\u5e74\u5ea7\u8c08\u4f1a\u4e0a\u7684\u8bb2\u8bdd","input_date":"2013-12-26 16:01:46","article_id":"23952651","publishdate":"0","publishdep":"","origin_name":"\u65b0\u534e\u7f51"},{"title":"\u4e2d\u5171\u4e2d\u592e\u4e3e\u884c\u7eaa\u5ff5\u6bdb\u6cfd\u4e1c\u540c\u5fd7\u8bde\u8fb0120\u5468\u5e74\u5ea7\u8c08\u4f1a \u4e60\u8fd1\u5e73\u53d1\u8868\u91cd\u8981\u8bb2\u8bdd","input_date":"2013-12-26 15:09:51","article_id":"23952301","publishdate":"0","publishdep":"","origin_name":"\u65b0\u534e\u7f51"},{"title":"\u4e2d\u5171\u4e2d\u592e\u4e3e\u884c\u7eaa\u5ff5\u6bdb\u6cfd\u4e1c\u540c\u5fd7\u8bde\u8fb0120\u5468\u5e74\u5ea7\u8c08\u4f1a \u4e60\u8fd1\u5e73\u53d1\u8868\u91cd\u8981\u8bb2\u8bdd","input_date":"2013-12-26 12:43:21","article_id":"23951234","publishdate":"0","publishdep":"","origin_name":"\u65b0\u534e\u7f51"},{"title":"\u4e60\u8fd1\u5e73\u7b49\u77bb\u4ef0\u6bdb\u6cfd\u4e1c\u540c\u5fd7\u9057\u5bb9","input_date":"2013-12-26 09:47:54","article_id":"23950116","publishdate":"0","publishdep":"","origin_name":"\u65b0\u534e\u7f51"},{"title":"\u4e2d\u592e\u519c\u6751\u5de5\u4f5c\u4f1a\u8bae\u5728\u5317\u4eac\u4e3e\u884c \u4e60\u8fd1\u5e73\u674e\u514b\u5f3a\u4f5c\u91cd\u8981\u8bb2\u8bdd","input_date":"2013-12-25 07:00:46","article_id":"23938145","publishdate":"0","publishdep":"","origin_name":"\u4eba\u6c11\u7f51\uff0d\u4eba\u6c11\u65e5\u62a5"},{"title":"\u4e2d\u592e\u519c\u6751\u5de5\u4f5c\u4f1a\u8bae\u5728\u5317\u4eac\u4e3e\u884c \u4e60\u8fd1\u5e73\u3001\u674e\u514b\u5f3a\u4f5c\u91cd\u8981\u8bb2\u8bdd","input_date":"2013-12-24 21:30:35","article_id":"23936629","publishdate":"0","publishdep":"","origin_name":"\u65b0\u534e\u7f51"},{"title":"\u4e60\u8fd1\u5e73\u4e3b\u5e2d\u4e0e\u73bb\u5229\u7ef4\u4e9a\u603b\u7edf\u83ab\u62c9\u83b1\u65af\u5c31\u73bb\u5229\u7ef4\u4e9a\u901a\u4fe1\u536b\u661f\u6210\u529f\u53d1\u5c04\u76f8\u4e92\u81f4\u8d3a","input_date":"2013-12-22 08:51:14","article_id":"23910471","publishdate":"0","publishdep":"","origin_name":"\u4eba\u6c11\u7f51\uff0d\u4eba\u6c11\u65e5\u62a5"},{"title":"\u4e60\u8fd1\u5e73\u5173\u4e8e\u6fb3\u95e8\u53d1\u5c55\u548c\u957f\u6cbb\u4e45\u5b89\u7684\u8868\u8ff0\u5f15\u53d1\u6fb3\u95e8\u793e\u4f1a\u70ed\u70c8\u53cd\u54cd","input_date":"2013-12-21 10:47:44","article_id":"23908004","publishdate":"0","publishdep":"","origin_name":"\u65b0\u534e\u7f51"}]}