{"status":"success","keywords":"","total":12153,"pages":"<em onclick=\"pageClick(1)\" style=\"cursor: default;\">\u9996\u9875<\/em><span onclick=\"pageClick(1160)\" style=\"cursor:default;\">1160<\/span><span onclick=\"pageClick(1161)\" style=\"cursor:default;\">1161<\/span><span class=\"active\" style=\"cursor:default;\">1162<\/span><span onclick=\"pageClick(1163)\" style=\"cursor:default;\">1163<\/span><span onclick=\"pageClick(1164)\" style=\"cursor:default;\">1164<\/span><em onclick=\"pageClick(1216)\" style=\"cursor: default;\">\u672b\u9875<\/em>","curPage":1162,"origin":"","list":[{"title":"\u4e60\u8fd1\u5e73\u8d70\u8bbf\u54e5\u65af\u8fbe\u9ece\u52a0\u519c\u6237","input_date":"2013-06-05 08:07:07","article_id":"21738936","publishdate":"0","publishdep":"","origin_name":"\u4eba\u6c11\u7f51\uff0d\u4eba\u6c11\u65e5\u62a5"},{"title":"\u4e60\u8fd1\u5e73\u4f1a\u89c1\u54e5\u65af\u8fbe\u9ece\u52a0\u7acb\u6cd5\u5927\u4f1a\u4e3b\u5e2d","input_date":"2013-06-05 08:06:26","article_id":"21738916","publishdate":"0","publishdep":"","origin_name":"\u4eba\u6c11\u7f51\uff0d\u4eba\u6c11\u65e5\u62a5"},{"title":"\u4e60\u8fd1\u5e73\uff1a\u4e2d\u54e5\u5173\u7cfb\u5b8c\u5168\u53ef\u4ee5\u6210\u4e3a\u4e0d\u540c\u89c4\u6a21 \u4e0d\u540c\u56fd\u60c5\u56fd\u5bb6\u53cb\u597d\u5408\u4f5c\u7684\u5178\u8303","input_date":"2013-06-05 08:06:26","article_id":"21738917","publishdate":"0","publishdep":"","origin_name":"\u4eba\u6c11\u7f51\uff0d\u4eba\u6c11\u65e5\u62a5"},{"title":"\u4e60\u8fd1\u5e73\u540c\u58a8\u897f\u54e5\u603b\u7edf\u57f9\u5c3c\u4e9a\u4e3e\u884c\u4f1a\u8c08","input_date":"2013-06-05 08:05:49","article_id":"21738907","publishdate":"0","publishdep":"","origin_name":"\u65b0\u534e\u7f51"},{"title":"\u4e60\u8fd1\u5e73\u540c\u54e5\u65af\u8fbe\u9ece\u52a0\u603b\u7edf\u5171\u540c\u4f1a\u89c1\u8bb0\u8005","input_date":"2013-06-04 16:55:21","article_id":"21734251","publishdate":"0","publishdep":"","origin_name":"\u65b0\u534e\u7f51"},{"title":"\u4e60\u8fd1\u5e73\u8d70\u8bbf\u54e5\u65af\u8fbe\u9ece\u52a0\u519c\u6237","input_date":"2013-06-04 16:30:47","article_id":"21733934","publishdate":"0","publishdep":"","origin_name":"\u65b0\u534e\u7f51"},{"title":"\u4e60\u8fd1\u5e73\u63a5\u53d7\u5723\u4f55\u585e\u57ce\u5e02\u94a5\u5319","input_date":"2013-06-04 08:58:05","article_id":"21726188","publishdate":"0","publishdep":"","origin_name":"\u65b0\u534e\u7f51"},{"title":"\u4e60\u8fd1\u5e73\u540c\u54e5\u65af\u8fbe\u9ece\u52a0\u603b\u7edf\u94a6\u5947\u5229\u4e9a\u4e3e\u884c\u4f1a\u8c08","input_date":"2013-06-04 08:32:31","article_id":"21725268","publishdate":"0","publishdep":"","origin_name":"\u65b0\u534e\u7f51"},{"title":"\u4e60\u8fd1\u5e73\u51fa\u5e2d\u54e5\u65af\u8fbe\u9ece\u52a0\u603b\u7edf\u94a6\u5947\u5229\u4e9a\u4e3e\u884c\u7684\u6b22\u8fce\u4eea\u5f0f\uff08\u56fe\uff09","input_date":"2013-06-04 08:27:51","article_id":"21725046","publishdate":"0","publishdep":"","origin_name":"\u65b0\u534e\u7f51"},{"title":"\u4e60\u8fd1\u5e73\u4f1a\u89c1\u54e5\u65af\u8fbe\u9ece\u52a0\u7acb\u6cd5\u5927\u4f1a\u4e3b\u5e2d\u95e8\u591a\u8428","input_date":"2013-06-04 08:26:05","article_id":"21724961","publishdate":"0","publishdep":"","origin_name":"\u65b0\u534e\u7f51"}]}